WeizhideShixianVol2/Dockerfile
WeizhideShixianVol2/README.md
WeizhideShixianVol2/__init__.py
WeizhideShixianVol2/__main__.py
WeizhideShixianVol2/file.epub
WeizhideShixianVol2/index.html
WeizhideShixianVol2/css/__init__.py
WeizhideShixianVol2/css/annotations.css
WeizhideShixianVol2/css/main.css
WeizhideShixianVol2/css/normalize.css
WeizhideShixianVol2/css/popup.css
WeizhideShixianVol2/font/__init__.py
WeizhideShixianVol2/font/fontello.eot
WeizhideShixianVol2/font/fontello.svg
WeizhideShixianVol2/font/fontello.ttf
WeizhideShixianVol2/font/fontello.woff
WeizhideShixianVol2/img/__init__.py
WeizhideShixianVol2/img/annotator-glyph-sprite.png
WeizhideShixianVol2/img/annotator-icon-sprite.png
WeizhideShixianVol2/img/apple-touch-icon.png
WeizhideShixianVol2/img/cancelfullscreen.png
WeizhideShixianVol2/img/close.png
WeizhideShixianVol2/img/fullscreen.png
WeizhideShixianVol2/img/loader.gif
WeizhideShixianVol2/img/menu-icon.png
WeizhideShixianVol2/img/save.png
WeizhideShixianVol2/img/saved.png
WeizhideShixianVol2/img/settings-s.png
WeizhideShixianVol2/img/settings.png
WeizhideShixianVol2/img/star.png
WeizhideShixianVol2/js/__init__.py
WeizhideShixianVol2/js/epub.js
WeizhideShixianVol2/js/epub.min.js
WeizhideShixianVol2/js/epub.min.map
WeizhideShixianVol2/js/hooks.min.js
WeizhideShixianVol2/js/hooks.min.map
WeizhideShixianVol2/js/reader.js
WeizhideShixianVol2/js/reader.js.map
WeizhideShixianVol2/js/reader.min.js
WeizhideShixianVol2/js/reader.min.map
WeizhideShixianVol2/js/hooks/__init__.py
WeizhideShixianVol2/js/hooks/extensions/__init__.py
WeizhideShixianVol2/js/hooks/extensions/highlight.js
WeizhideShixianVol2/js/libs/__init__.py
WeizhideShixianVol2/js/libs/jquery.min.js
WeizhideShixianVol2/js/libs/localforage.min.js
WeizhideShixianVol2/js/libs/screenfull.js
WeizhideShixianVol2/js/libs/screenfull.min.js
WeizhideShixianVol2/js/libs/zip.min.js
WeizhideShixianVol2/js/plugins/__init__.py
WeizhideShixianVol2/js/plugins/hypothesis.js
WeizhideShixianVol2/js/plugins/search.js
weizhide_shixian_vol2-2022.10.9.1.dist-info/METADATA
weizhide_shixian_vol2-2022.10.9.1.dist-info/WHEEL
weizhide_shixian_vol2-2022.10.9.1.dist-info/entry_points.txt
weizhide_shixian_vol2-2022.10.9.1.dist-info/top_level.txt
weizhide_shixian_vol2-2022.10.9.1.dist-info/RECORD
